{
  "ID": "f6aa6e87-78c8-4dff-a95d-8f238ed423dc",
  "Version": "2.3.2.3",
  "Name": "Layer1",
  "Content": {
    "Content": {
      "Animation": {
        "Duration": 60,
        "Speed": 2.0,
        "Timelines": [
          {
            "ActionTag": -857326657,
            "Property": "Position",
            "Frames": [
              {
                "X": 209.9327,
                "Y": -194.4633,
                "FrameIndex": 0,
                "EasingData": {
                  "Type": 3
                },
                "ctype": "PointFrameData"
              },
              {
                "X": 209.9324,
                "Y": 355.5372,
                "FrameIndex": 30,
                "EasingData": {
                  "Type": 0
                },
                "ctype": "PointFrameData"
              }
            ],
            "ctype": "TimelineData"
          },
          {
            "ActionTag": -857326657,
            "Property": "Scale",
            "Frames": [
              {
                "X": 1.0,
                "Y": 1.0,
                "FrameIndex": 0,
                "EasingData": {
                  "Type": 3
                },
                "ctype": "ScaleValueFrameData"
              },
              {
                "X": 1.0,
                "Y": 1.0,
                "FrameIndex": 30,
                "EasingData": {
                  "Type": 0
                },
                "ctype": "ScaleValueFrameData"
              }
            ],
            "ctype": "TimelineData"
          },
          {
            "ActionTag": -857326657,
            "Property": "RotationSkew",
            "Frames": [
              {
                "X": 0.0,
                "Y": 0.0,
                "FrameIndex": 0,
                "EasingData": {
                  "Type": 3
                },
                "ctype": "ScaleValueFrameData"
              },
              {
                "X": 0.0,
                "Y": 0.0,
                "FrameIndex": 30,
                "EasingData": {
                  "Type": 0
                },
                "ctype": "ScaleValueFrameData"
              }
            ],
            "ctype": "TimelineData"
          },
          {
            "ActionTag": 1687021666,
            "Property": "Position",
            "Frames": [
              {
                "X": 478.8119,
                "Y": -194.4633,
                "FrameIndex": 20,
                "EasingData": {
                  "Type": 3
                },
                "ctype": "PointFrameData"
              },
              {
                "X": 478.8123,
                "Y": 355.5372,
                "FrameIndex": 50,
                "EasingData": {
                  "Type": 0
                },
                "ctype": "PointFrameData"
              }
            ],
            "ctype": "TimelineData"
          },
          {
            "ActionTag": 1687021666,
            "Property": "Scale",
            "Frames": [
              {
                "X": 1.0,
                "Y": 1.0,
                "FrameIndex": 20,
                "EasingData": {
                  "Type": 3
                },
                "ctype": "ScaleValueFrameData"
              },
              {
                "X": 1.0,
                "Y": 1.0,
                "FrameIndex": 50,
                "EasingData": {
                  "Type": 0
                },
                "ctype": "ScaleValueFrameData"
              }
            ],
            "ctype": "TimelineData"
          },
          {
            "ActionTag": 1687021666,
            "Property": "RotationSkew",
            "Frames": [
              {
                "X": 0.0,
                "Y": 0.0,
                "FrameIndex": 20,
                "EasingData": {
                  "Type": 3
                },
                "ctype": "ScaleValueFrameData"
              },
              {
                "X": 0.0,
                "Y": 0.0,
                "FrameIndex": 50,
                "EasingData": {
                  "Type": 0
                },
                "ctype": "ScaleValueFrameData"
              }
            ],
            "ctype": "TimelineData"
          },
          {
            "ActionTag": 2062934783,
            "Property": "Position",
            "Frames": [
              {
                "X": 334.4817,
                "Y": -334.2135,
                "FrameIndex": 30,
                "EasingData": {
                  "Type": 3
                },
                "ctype": "PointFrameData"
              },
              {
                "X": 334.4818,
                "Y": 205.7869,
                "FrameIndex": 60,
                "EasingData": {
                  "Type": 0
                },
                "ctype": "PointFrameData"
              }
            ],
            "ctype": "TimelineData"
          },
          {
            "ActionTag": 2062934783,
            "Property": "Scale",
            "Frames": [
              {
                "X": 1.0,
                "Y": 1.0,
                "FrameIndex": 30,
                "EasingData": {
                  "Type": 3
                },
                "ctype": "ScaleValueFrameData"
              },
              {
                "X": 1.0,
                "Y": 1.0,
                "FrameIndex": 60,
                "EasingData": {
                  "Type": 0
                },
                "ctype": "ScaleValueFrameData"
              }
            ],
            "ctype": "TimelineData"
          },
          {
            "ActionTag": 2062934783,
            "Property": "RotationSkew",
            "Frames": [
              {
                "X": 0.0,
                "Y": 0.0,
                "FrameIndex": 30,
                "EasingData": {
                  "Type": 3
                },
                "ctype": "ScaleValueFrameData"
              },
              {
                "X": 0.0,
                "Y": 0.0,
                "FrameIndex": 60,
                "EasingData": {
                  "Type": 0
                },
                "ctype": "ScaleValueFrameData"
              }
            ],
            "ctype": "TimelineData"
          }
        ],
        "ctype": "TimelineActionData"
      },
      "AnimationList": [],
      "ObjectData": {
        "Tag": 20,
        "Children": [
          {
            "FileData": {
              "Type": "Normal",
              "Path": "gameover.png",
              "Plist": ""
            },
            "Scale9Width": 358,
            "Scale9Height": 60,
            "AnchorPoint": {
              "ScaleX": 0.5,
              "ScaleY": 0.5
            },
            "Position": {
              "X": 337.3224,
              "Y": 760.7108
            },
            "Scale": {
              "ScaleX": 1.0,
              "ScaleY": 1.0
            },
            "CColor": {},
            "IconVisible": false,
            "PrePosition": {
              "X": 0.5271,
              "Y": 0.7924
            },
            "PreSize": {
              "X": 0.5594,
              "Y": 0.0625
            },
            "LeftMargin": 158.3224,
            "RightMargin": 123.6776,
            "TopMargin": 169.2892,
            "BottomMargin": 730.7108,
            "Tag": 52,
            "ActionTag": 1593159560,
            "Size": {
              "X": 358.0,
              "Y": 60.0
            },
            "Name": "Image_3",
            "ctype": "ImageViewObjectData"
          },
          {
            "FileData": {
              "Type": "Normal",
              "Path": "curscore.png",
              "Plist": ""
            },
            "Scale9Width": 248,
            "Scale9Height": 61,
            "AnchorPoint": {
              "ScaleX": 0.5,
              "ScaleY": 0.5
            },
            "Position": {
              "X": 199.1812,
              "Y": 633.6527
            },
            "Scale": {
              "ScaleX": 1.0,
              "ScaleY": 1.0
            },
            "CColor": {},
            "IconVisible": false,
            "PrePosition": {
              "X": 0.3112,
              "Y": 0.6601
            },
            "PreSize": {
              "X": 0.3875,
              "Y": 0.0635
            },
            "LeftMargin": 75.1812,
            "RightMargin": 316.8188,
            "TopMargin": 295.8473,
            "BottomMargin": 603.1527,
            "Tag": 53,
            "ActionTag": 768619859,
            "Size": {
              "X": 248.0,
              "Y": 61.0
            },
            "Name": "Image_4",
            "ctype": "ImageViewObjectData"
          },
          {
            "FileData": {
              "Type": "Normal",
              "Path": "bestscore.png",
              "Plist": ""
            },
            "Scale9Width": 254,
            "Scale9Height": 64,
            "AnchorPoint": {
              "ScaleX": 0.5,
              "ScaleY": 0.5
            },
            "Position": {
              "X": 202.1813,
              "Y": 494.4285
            },
            "Scale": {
              "ScaleX": 1.0,
              "ScaleY": 1.0
            },
            "CColor": {},
            "IconVisible": false,
            "PrePosition": {
              "X": 0.3159,
              "Y": 0.515
            },
            "PreSize": {
              "X": 0.3969,
              "Y": 0.0667
            },
            "LeftMargin": 75.1813,
            "RightMargin": 310.8187,
            "TopMargin": 433.5715,
            "BottomMargin": 462.4285,
            "Tag": 54,
            "ActionTag": 1018273744,
            "Size": {
              "X": 254.0,
              "Y": 64.0
            },
            "Name": "Image_5",
            "ctype": "ImageViewObjectData"
          },
          {
            "FontSize": 70,
            "LabelText": "600",
            "OutlineColor": {
              "G": 0,
              "B": 0
            },
            "ShadowColor": {
              "R": 110,
              "G": 110,
              "B": 110
            },
            "ShadowOffsetX": 2.0,
            "ShadowOffsetY": -2.0,
            "AnchorPoint": {
              "ScaleX": 0.5,
              "ScaleY": 0.5
            },
            "Position": {
              "X": 477.5667,
              "Y": 636.6699
            },
            "Scale": {
              "ScaleX": 1.0,
              "ScaleY": 1.0
            },
            "CColor": {
              "G": 0,
              "B": 0
            },
            "IconVisible": false,
            "PrePosition": {
              "X": 0.7462,
              "Y": 0.6632
            },
            "PreSize": {
              "X": 0.0,
              "Y": 0.0
            },
            "LeftMargin": 425.0667,
            "RightMargin": 109.9333,
            "TopMargin": 288.3301,
            "BottomMargin": 601.6699,
            "Tag": 67,
            "ActionTag": -686305612,
            "Size": {
              "X": 105.0,
              "Y": 70.0
            },
            "Name": "Text_Cu",
            "ctype": "TextObjectData"
          },
          {
            "FontSize": 70,
            "LabelText": "300",
            "OutlineColor": {
              "G": 0,
              "B": 0
            },
            "ShadowColor": {
              "R": 110,
              "G": 110,
              "B": 110
            },
            "ShadowOffsetX": 2.0,
            "ShadowOffsetY": -2.0,
            "AnchorPoint": {
              "ScaleX": 0.5,
              "ScaleY": 0.5
            },
            "Position": {
              "X": 477.5667,
              "Y": 492.8206
            },
            "Scale": {
              "ScaleX": 1.0,
              "ScaleY": 1.0
            },
            "CColor": {
              "G": 0,
              "B": 0
            },
            "IconVisible": false,
            "PrePosition": {
              "X": 0.7462,
              "Y": 0.5134
            },
            "PreSize": {
              "X": 0.0,
              "Y": 0.0
            },
            "LeftMargin": 425.0667,
            "RightMargin": 109.9333,
            "TopMargin": 432.1794,
            "BottomMargin": 457.8206,
            "Tag": 68,
            "ActionTag": 2016057280,
            "Size": {
              "X": 105.0,
              "Y": 70.0
            },
            "Name": "Text_Best",
            "ctype": "TextObjectData"
          },
          {
            "FontSize": 14,
            "ButtonText": "",
            "TextColor": {
              "R": 65,
              "G": 65,
              "B": 70
            },
            "DisabledFileData": {
              "Type": "Default",
              "Path": "Default/Button_Disable.png",
              "Plist": ""
            },
            "PressedFileData": {
              "Type": "Default",
              "Path": "Default/Button_Press.png",
              "Plist": ""
            },
            "NormalFileData": {
              "Type": "Normal",
              "Path": "replaybtn.png",
              "Plist": ""
            },
            "Scale9Enable": true,
            "Scale9OriginX": 15,
            "Scale9OriginY": 11,
            "Scale9Width": 209,
            "Scale9Height": 60,
            "OutlineColor": {
              "G": 0,
              "B": 0
            },
            "ShadowColor": {
              "R": 110,
              "G": 110,
              "B": 110
            },
            "ShadowOffsetX": 2.0,
            "ShadowOffsetY": -2.0,
            "TouchEnable": true,
            "AnchorPoint": {
              "ScaleX": 0.5,
              "ScaleY": 0.5
            },
            "Position": {
              "X": 209.9325,
              "Y": 192.3896
            },
            "Scale": {
              "ScaleX": 1.0,
              "ScaleY": 1.0
            },
            "CColor": {},
            "IconVisible": false,
            "PrePosition": {
              "X": 0.328,
              "Y": 0.2004
            },
            "PreSize": {
              "X": 0.3734,
              "Y": 0.0854
            },
            "LeftMargin": 90.4325,
            "RightMargin": 310.5675,
            "TopMargin": 726.6104,
            "BottomMargin": 151.3896,
            "Tag": 104,
            "ActionTag": -857326657,
            "Size": {
              "X": 239.0,
              "Y": 82.0
            },
            "Name": "Btn_Again",
            "ctype": "ButtonObjectData"
          },
          {
            "FontSize": 14,
            "ButtonText": "",
            "TextColor": {
              "R": 65,
              "G": 65,
              "B": 70
            },
            "DisabledFileData": {
              "Type": "Default",
              "Path": "Default/Button_Disable.png",
              "Plist": ""
            },
            "PressedFileData": {
              "Type": "Default",
              "Path": "Default/Button_Press.png",
              "Plist": ""
            },
            "NormalFileData": {
              "Type": "Normal",
              "Path": "toplistbtn.png",
              "Plist": ""
            },
            "Scale9Enable": true,
            "Scale9OriginX": 15,
            "Scale9OriginY": 11,
            "Scale9Width": 209,
            "Scale9Height": 60,
            "OutlineColor": {
              "G": 0,
              "B": 0
            },
            "ShadowColor": {
              "R": 110,
              "G": 110,
              "B": 110
            },
            "ShadowOffsetX": 2.0,
            "ShadowOffsetY": -2.0,
            "TouchEnable": true,
            "AnchorPoint": {
              "ScaleX": 0.5,
              "ScaleY": 0.5
            },
            "Position": {
              "X": 478.8119,
              "Y": -194.4633
            },
            "Scale": {
              "ScaleX": 1.0,
              "ScaleY": 1.0
            },
            "CColor": {},
            "IconVisible": false,
            "PrePosition": {
              "X": 0.7481,
              "Y": -0.2026
            },
            "PreSize": {
              "X": 0.3734,
              "Y": 0.0854
            },
            "LeftMargin": 359.3119,
            "RightMargin": 41.6881,
            "TopMargin": 1113.4633,
            "BottomMargin": -235.4633,
            "Tag": 105,
            "ActionTag": 1687021666,
            "Size": {
              "X": 239.0,
              "Y": 82.0
            },
            "Name": "Btn_TopList",
            "ctype": "ButtonObjectData"
          },
          {
            "FontSize": 14,
            "ButtonText": "",
            "TextColor": {
              "R": 65,
              "G": 65,
              "B": 70
            },
            "DisabledFileData": {
              "Type": "Default",
              "Path": "Default/Button_Disable.png",
              "Plist": ""
            },
            "PressedFileData": {
              "Type": "Default",
              "Path": "Default/Button_Press.png",
              "Plist": ""
            },
            "NormalFileData": {
              "Type": "Normal",
              "Path": "lowkeysharebtn.png",
              "Plist": ""
            },
            "Scale9Enable": true,
            "Scale9OriginX": 15,
            "Scale9OriginY": 11,
            "Scale9Width": 219,
            "Scale9Height": 60,
            "OutlineColor": {
              "G": 0,
              "B": 0
            },
            "ShadowColor": {
              "R": 110,
              "G": 110,
              "B": 110
            },
            "ShadowOffsetX": 2.0,
            "ShadowOffsetY": -2.0,
            "TouchEnable": true,
            "AnchorPoint": {
              "ScaleX": 0.5,
              "ScaleY": 0.5
            },
            "Position": {
              "X": 334.4817,
              "Y": -334.2135
            },
            "Scale": {
              "ScaleX": 1.0,
              "ScaleY": 1.0
            },
            "CColor": {},
            "IconVisible": false,
            "PrePosition": {
              "X": 0.5226,
              "Y": -0.3481
            },
            "PreSize": {
              "X": 0.3891,
              "Y": 0.0854
            },
            "LeftMargin": 209.9817,
            "RightMargin": 181.0183,
            "TopMargin": 1253.2135,
            "BottomMargin": -375.2135,
            "Tag": 106,
            "ActionTag": 2062934783,
            "Size": {
              "X": 249.0,
              "Y": 82.0
            },
            "Name": "Btn_LowKeyShare",
            "ctype": "ButtonObjectData"
          }
        ],
        "Size": {
          "X": 640.0,
          "Y": 960.0
        },
        "Name": "Layer",
        "ctype": "LayerObjectData"
      },
      "UsedResources": [
        "bestscore.png",
        "curscore.png",
        "Default/Button_Disable.png",
        "Default/Button_Press.png",
        "gameover.png",
        "lowkeysharebtn.png",
        "replaybtn.png",
        "toplistbtn.png"
      ],
      "ctype": "GameProjectData"
    }
  },
  "Type": "Layer"
}